georinex/__init__.py
georinex/base.py
georinex/common.py
georinex/geo.py
georinex/keplerian.py
georinex/nav2.py
georinex/nav3.py
georinex/obs2.py
georinex/obs3.py
georinex/plots.py
georinex/plots_geo.py
georinex/rio.py
georinex/sp3.py
georinex/utils.py
georinex/versions.py
georinex/loc/__init__.py
georinex/loc/__main__.py
georinex/plot/__init__.py
georinex/plot/__main__.py
georinex/read/__init__.py
georinex/read/__main__.py
georinex/rinex2hdf5/__init__.py
georinex/rinex2hdf5/__main__.py
georinex/tests/test_batch_convert.py
georinex/tests/test_conv.py
georinex/tests/test_hatanaka.py
georinex/tests/test_header.py
georinex/tests/test_kepler.py
georinex/tests/test_lzw.py
georinex/tests/test_nav2.py
georinex/tests/test_nav3.py
georinex/tests/test_obs2.py
georinex/tests/test_obs3.py
georinex/tests/test_rinex.py
georinex/tests/test_scripts.py
georinex/tests/test_sp3.py
georinex/tests/test_stringio.py
georinex/tests/test_time.py
georinex/time/__init__.py
georinex/time/__main__.py
georinex-1.16.2.dist-info/LICENSE.txt
georinex-1.16.2.dist-info/METADATA
georinex-1.16.2.dist-info/WHEEL
georinex-1.16.2.dist-info/top_level.txt
georinex-1.16.2.dist-info/RECORD
