Metadata-Version: 2.1
Name: georinex
Version: 1.16.2
Summary: Python RINEX 2/3 NAV/OBS reader with speed and simplicity.
Keywords: RINEX,sp3,HDF5,NetCDF4
Classifier: Development Status :: 5 - Production/Stable
Classifier: Environment :: Console
Classifier: Intended Audience :: Science/Research
Classifier: License :: OSI Approved :: MIT License
Classifier: Operating System :: OS Independent
Classifier: Programming Language :: Python :: 3
Classifier: Topic :: Scientific/Engineering :: Atmospheric Science
Requires-Python: >=3.8
License-File: LICENSE.txt
Requires-Dist: python-dateutil
Requires-Dist: numpy
Requires-Dist: xarray
Requires-Dist: hatanaka
Requires-Dist: ncompress
Requires-Dist: netcdf4
Provides-Extra: tests
Requires-Dist: pytest; extra == "tests"
Requires-Dist: pytest-timeout; extra == "tests"
Provides-Extra: lint
Requires-Dist: flake8; extra == "lint"
Requires-Dist: flake8-bugbear; extra == "lint"
Requires-Dist: flake8-builtins; extra == "lint"
Requires-Dist: flake8-blind-except; extra == "lint"
Requires-Dist: mypy; extra == "lint"
Requires-Dist: types-python-dateutil; extra == "lint"
Provides-Extra: plot
Requires-Dist: matplotlib; extra == "plot"
Requires-Dist: seaborn; extra == "plot"
Requires-Dist: pymap3d; extra == "plot"
Requires-Dist: cartopy; extra == "plot"
Provides-Extra: io
Requires-Dist: psutil; extra == "io"
